bomist_utils/__init__.py
bomist_utils/cli.py
bomist_utils/crypto.py
bomist_utils/legacy.py
bomist_utils/v2.py
bomist_utils-0.1.12.dist-info/entry_points.txt
bomist_utils-0.1.12.dist-info/WHEEL
bomist_utils-0.1.12.dist-info/METADATA
bomist_utils-0.1.12.dist-info/RECORD
