Metadata-Version: 2.1
Name: bomist-utils
Version: 0.1.12
Summary: BOMIST Utilities
Home-page: https://bomist.com
Keywords: bomist
Author: Mario Ribeiro
Author-email: mario@bomist.com
Requires-Python: >=3.7,<4.0
Classifier: Programming Language :: Python :: 3
Classifier: Programming Language :: Python :: 3.7
Classifier: Programming Language :: Python :: 3.8
Classifier: Programming Language :: Python :: 3.9
